hack4u/__init__.py
hack4u/courses.py
hack4u/utils.py
h4ufinder-0.5.0.dist-info/METADATA
h4ufinder-0.5.0.dist-info/WHEEL
h4ufinder-0.5.0.dist-info/top_level.txt
h4ufinder-0.5.0.dist-info/RECORD
