Metadata-Version: 2.1
Name: h4ufinder
Version: 0.5.0
Summary: Una biblioteca para consultar cursos de hack4u
Home-page: https://hack4u.io
Author: HR10
